dependamerge/__init__.py
dependamerge/_version.py
dependamerge/cli.py
dependamerge/close_manager.py
dependamerge/copilot_handler.py
dependamerge/error_codes.py
dependamerge/git_ops.py
dependamerge/github_async.py
dependamerge/github_client.py
dependamerge/github_graphql.py
dependamerge/github_service.py
dependamerge/merge_manager.py
dependamerge/models.py
dependamerge/output_utils.py
dependamerge/pr_comparator.py
dependamerge/progress_tracker.py
dependamerge/py.typed
dependamerge/resolve_conflicts.py
dependamerge/system_utils.py
dependamerge-0.1.19.dist-info/METADATA
dependamerge-0.1.19.dist-info/WHEEL
dependamerge-0.1.19.dist-info/entry_points.txt
dependamerge-0.1.19.dist-info/licenses/LICENSE
dependamerge-0.1.19.dist-info/RECORD
