Metadata-Version: 2.4
Name: dependamerge
Version: 0.1.19
Summary: Bulk pull request management tool for GitHub organisations
Project-URL: Homepage, https://github.com/lfit/dependamerge
Project-URL: Repository, https://github.com/lfit/dependamerge
Project-URL: Downloads, https://github.com/lfit/dependamerge/releases
Project-URL: Bug Tracker, https://github.com/lfit/dependamerge/issues
Project-URL: Documentation, https://github.com/lfit/dependamerge/tree/main/docs
Project-URL: Source Code, https://github.com/lfit/dependamerge
Author-email: Matthew Watkins <93649628+ModeSevenIndustrialSolutions@users.noreply.github.com>
License-Expression: Apache-2.0
License-File: LICENSE
Classifier: Intended Audience :: Developers
Classifier: Intended Audience :: Science/Research
Classifier: Operating System :: MacOS
Classifier: Operating System :: Microsoft :: Windows
Classifier: Operating System :: Unix
Classifier: Programming Language :: Python
Classifier: Programming Language :: Python :: 3
Classifier: Programming Language :: Python :: 3 :: Only
Classifier: Programming Language :: Python :: 3.10
Classifier: Programming Language :: Python :: 3.11
Classifier: Programming Language :: Python :: 3.12
Classifier: Programming Language :: Python :: 3.13
Classifier: Programming Language :: Python :: 3.14
Classifier: Topic :: Software Development
Requires-Python: >=3.10
Requires-Dist: aiolimiter>=1.2.1
Requires-Dist: httpx[http2]>=0.28.1
Requires-Dist: pydantic>=2.12.5
Requires-Dist: requests>=2.32.5
Requires-Dist: rich>=14.2.0
Requires-Dist: tenacity>=9.1.2
Requires-Dist: typer>=0.20.0
Provides-Extra: dev
Requires-Dist: black>=25.1.0; extra == 'dev'
Requires-Dist: coverage[toml]>=7.6.9; extra == 'dev'
Requires-Dist: flake8>=7.3.0; extra == 'dev'
Requires-Dist: mypy>=1.17.1; extra == 'dev'
Requires-Dist: pyflakes>=3.4.0; extra == 'dev'
Requires-Dist: pytest-asyncio>=1.1.0; extra == 'dev'
Requires-Dist: pytest-cov>=7.0.0; extra == 'dev'
Requires-Dist: pytest-mock>=3.15.1; extra == 'dev'
Requires-Dist: pytest>=9.0.2; extra == 'dev'
Requires-Dist: responses>=0.25.8; extra == 'dev'
Requires-Dist: types-requests>=2.32.4.20250809; extra == 'dev'
